sigen.py
sigen-3.0.1.dist-info/METADATA
sigen-3.0.1.dist-info/WHEEL
sigen-3.0.1.dist-info/licenses/LICENSE
sigen-3.0.1.dist-info/RECORD
