Metadata-Version: 2.4
Name: sigen
Version: 3.0.1
Summary: Interacts with Sigenergy cloud APIs to read and write data to and from inverters. For local control, use Modbus instead.
Project-URL: Homepage, https://github.com/fbradyirl/sigen
Project-URL: Issues, https://github.com/fbradyirl/sigen/issues
Author-email: Example Author <author@example.com>
License-File: LICENSE
Classifier: License :: OSI Approved :: MIT License
Classifier: Operating System :: OS Independent
Classifier: Programming Language :: Python :: 3
Requires-Python: >=3.12
Requires-Dist: aiohttp
Requires-Dist: pycryptodome
Requires-Dist: requests
